{
  "@context": "https://www.w3.org/ns/activitystreams",
  "type": "Create",
  "actor": "https://finnleijen.eu/activitypub/profile.json",
  "id": "https://finnleijen.eu/activitypub/IMG_1508.JPG.json",
  "published": "2025-03-08T09:43:30.000Z",
  "object": {
    "id": "https://finnleijen.eu/activitypub/IMG_1508.JPG.json",
    "type": "Article",
    "name": "Hello World 5 ig... yet another try",
    "content": "\n        In this post, I am ch an image, as this was the issue before.<br>\n        <img src=\"https://www.finnleijen.eu/2024/IMG_1508.JPG\">\n      ",
    "url": "https://www.finnleijen.eu/2024/IMG_1508.JPG"
  }
}